xyt/__init__.py
xyt/fake_data_generator.py
xyt/gps_analytics.py
xyt/gps_data_privacy.py
xyt/gps_data_processor.py
xyt/gps_to_actionspace.py
xyt/gps_to_graph.py
xyt/xyt_plot.py
xyt-0.1.2.dist-info/LICENSE
xyt-0.1.2.dist-info/METADATA
xyt-0.1.2.dist-info/WHEEL
xyt-0.1.2.dist-info/RECORD
