Metadata-Version: 2.1
Name: xyt
Version: 0.1.2
Summary: xyt is a python package for processing raw gps data into mobility data. xyt offers privacy-based capabilities and aims to provide a plug-and-play pipeline to leverage gps data.
License: MIT
Keywords: xyt,gps,mobility
Author: Marc-Edouard Schultheiss
Author-email: meschultheiss@gmail.com
Maintainer: Marc-Edouard Schultheiss
Maintainer-email: meschultheiss@gmail.com
Requires-Python: >=3.6,<4.0
Classifier: License :: OSI Approved :: MIT License
Classifier: Operating System :: OS Independent
Classifier: Programming Language :: Python :: 3
Classifier: Programming Language :: Python :: 3.6
Classifier: Programming Language :: Python :: 3.7
Classifier: Programming Language :: Python :: 3.8
Classifier: Programming Language :: Python :: 3.9
Classifier: Programming Language :: Python :: 3.10
Classifier: Programming Language :: Python :: 3.11
Classifier: Programming Language :: Python :: 3.12
Requires-Dist: contextily
Requires-Dist: faker
Requires-Dist: folium
Requires-Dist: geopandas
Requires-Dist: geopy
Requires-Dist: gif
Requires-Dist: haversine
Requires-Dist: ipython
Requires-Dist: more-itertools
Requires-Dist: numba
Requires-Dist: numpy
Requires-Dist: osmnx
Requires-Dist: pandas
Requires-Dist: pathos
Requires-Dist: plotly
Requires-Dist: pointpats
Requires-Dist: pysal
Requires-Dist: scikit-fuzzy
Requires-Dist: scikit-learn
Requires-Dist: seaborn
Requires-Dist: shapely
Requires-Dist: streamlit-folium
Requires-Dist: utm
